<?xml version="1.0" encoding="UTF-8" ?>

<!DOCTYPE properties SYSTEM "http://java.sun.com/dtd/properties.dtd">
<properties>
    <comment>Domain resources for DicomSeries</comment>

    <entry key="dicomSeries">DICOM Series</entry>
    <entry key="dicomSeries_plural">DICOM Series</entry>
    <entry key="dicomSeries_reload">Reload existing DICOM Series</entry>
    <entry key="dicomSeries_print">Print DICOM Series table</entry>
    <entry key="dicomSeries_new">Define a new DICOM Series</entry>
    <entry key="dicomSeries_edit">Edit selected DICOM Series</entry>
    <entry key="dicomSeries_delete">Delete selected DICOM Series</entry>

    <!-- attributes -->
    <entry key="dicomSeries_id">Id</entry>
    <entry key="dicomSeries_seriesInstanceUID">UID</entry>
    <entry key="dicomSeries_seriesDescription">Description</entry>
    <entry key="dicomSeries_modality">Modality</entry>
    <entry key="dicomSeries_seriesTime">Time</entry>
    <entry key="dicomSeries_seriesDate">Date</entry>
    <entry key="dicomSeries_details">Details</entry>
    <entry key="dicomSeries_dicomDetails">DICOM Details</entry>
    <entry key="dicomSeries_regions_of_interest">Regions of Interest</entry>

</properties>