<?xml version="1.0" encoding="UTF-8"?>
<databaseChangeLog
    xmlns="http://www.liquibase.org/xml/ns/dbchangelog/1.9"
    xmlns:xsi="http://www.w3.org/2001/XMLSchema-instance"
    xsi:schemaLocation="http://www.liquibase.org/xml/ns/dbchangelog/1.9 http://www.liquibase.org/xml/ns/dbchangelog/dbchangelog-1.9.xsd"
    >
    <!-- Evolution of DB schema -->
    <include file="db.changelog.1.0.0.0.xml" />
    <include file="db.changelog.1.0.0.1.xml" />
    <include file="db.changelog.1.0.0.2.xml" />
    <include file="db.changelog.1.0.0.3.xml" />
    <include file="db.changelog.1.0.0.4.xml" />
    <include file="db.changelog.1.0.0.5.xml" />
    <include file="db.changelog.1.0.0.6.xml" />
    <include file="db.changelog.1.0.0.7.xml" />
    <include file="db.changelog.1.0.0.8.xml" />
    <include file="db.changelog.1.0.0.9.xml" />
    <include file="db.changelog.1.0.0.10.xml" />
    <include file="db.changelog.1.0.0.11.xml" />
    <include file="db.changelog.1.0.0.12.xml" />
    <include file="db.changelog.1.0.0.13.xml" />
</databaseChangeLog>
