<?xml version="1.0" encoding="UTF-8" ?>

<!DOCTYPE properties SYSTEM "http://java.sun.com/dtd/properties.dtd">
<properties>
    <comment>Domain resources for PersonStatus</comment>

    <entry key="personStatus">Status</entry>
    <entry key="personStatus_plural">Statuses</entry>
    <entry key="personStatus_reload">Neu laden vorhandenen Statuses</entry>
    <entry key="personStatus_print">Drucken Tabelle Statuses</entry>
    <entry key="personStatus_new">Definieren Sie eine neue Status</entry>
    <entry key="personStatus_edit">Bearbeiten Sie ausgewählte Status</entry>
    <entry key="personStatus_delete">Löschen ausgewählten Status</entry>

    <!-- attributes -->
    <entry key="personStatus_id">Id</entry>
    <entry key="personStatus_name">Name</entry>
    <entry key="personStatus_description">Beschreibung</entry>

</properties>